report_builder/__init__.py
report_builder/admin.py
report_builder/email.py
report_builder/mixins.py
report_builder/models.py
report_builder/tasks.py
report_builder/unique_slugify.py
report_builder/urls.py
report_builder/utils.py
report_builder/views.py
report_builder/api/__init__.py
report_builder/api/serializers.py
report_builder/api/tests.py
report_builder/api/views.py
report_builder/migrations/0001_initial.py
report_builder/migrations/0002_auto_20150201_1809.py
report_builder/migrations/0003_auto_20150720_1549.py
report_builder/migrations/0004_auto_20170915_2046.py
report_builder/migrations/0005_add_delta_filtering.py
report_builder/migrations/0006_auto_20180413_0747.py
report_builder/migrations/0007_auto_20190214_1405.py
report_builder/migrations/__init__.py
report_builder/static/report_builder/main-es2015.js
report_builder/static/report_builder/main-es5.js
report_builder/static/report_builder/polyfills-es2015.js
report_builder/static/report_builder/polyfills-es5.js
report_builder/static/report_builder/runtime-es2015.js
report_builder/static/report_builder/runtime-es5.js
report_builder/static/report_builder/styles.css
report_builder/static/report_builder/img/add.svg
report_builder/static/report_builder/img/arrow.png
report_builder/static/report_builder/img/arrow_down.png
report_builder/static/report_builder/img/copy.svg
report_builder/static/report_builder/img/delete.svg
report_builder/static/report_builder/img/download.svg
report_builder/static/report_builder/img/edit.png
report_builder/static/report_builder/img/edit.svg
report_builder/static/report_builder/img/list.svg
report_builder/static/report_builder/img/plus.png
report_builder/static/report_builder/img/reorder.svg
report_builder/static/report_builder/img/star.png
report_builder/static/report_builder/img/star.svg
report_builder/static/report_builder/img/unstar.png
report_builder/static/report_builder/js/report_form.js
report_builder/static/report_builder/js/report_list.js
django_report_builder_rq0-6.3.3.3.dist-info/LICENSE
django_report_builder_rq0-6.3.3.3.dist-info/METADATA
django_report_builder_rq0-6.3.3.3.dist-info/WHEEL
django_report_builder_rq0-6.3.3.3.dist-info/top_level.txt
django_report_builder_rq0-6.3.3.3.dist-info/RECORD
