Metadata-Version: 2.1
Name: django-report-builder-rq0
Version: 6.3.3.3
Summary: Query and Report builder for Django ORM
Home-page: https://github.com/Rq0/django-report-builder
Author: Aleksey Tartynskiy
Author-email: redisk0gg@gmail.com
License: BSD
Keywords: django report
Platform: UNKNOWN
Classifier: Development Status :: 5 - Production/Stable
Classifier: Environment :: Web Environment
Classifier: Framework :: Django
Classifier: Programming Language :: Python
Classifier: Programming Language :: Python :: 3
Classifier: Intended Audience :: Developers
Classifier: Intended Audience :: System Administrators
Classifier: License :: OSI Approved :: BSD License
Requires-Python: >=3.3
Requires-Dist: djangorestframework (>=3.8.0)
Requires-Dist: openpyxl (>=2.2.1)
Requires-Dist: python-dateutil
Requires-Dist: six
